[
  {
    "id": "cat-001",
    "slug": "ethereal",
    "title": "Ethereal / Angelic Icons",
    "coverAssetId": "nv-003",
    "visible": false,
    "order": 1,
    "filter": {
      "type": "tags",
      "tags": [
        "angelic"
      ]
    },
    "count": 0,
    "image": ""
  },
  {
    "id": "cat-002",
    "slug": "gothic",
    "title": "Dark / Gothic Icons",
    "coverAssetId": "nv-005",
    "visible": false,
    "order": 2,
    "filter": {
      "type": "tags",
      "tags": [
        "gothic"
      ]
    },
    "count": 0,
    "image": ""
  },
  {
    "id": "cat-003",
    "slug": "anime",
    "title": "Anime / Girl Icons",
    "coverAssetId": "nv-006",
    "visible": false,
    "order": 3,
    "filter": {
      "type": "tags",
      "tags": [
        "anime"
      ]
    },
    "count": 0,
    "image": ""
  },
  {
    "id": "cat-004",
    "slug": "matching",
    "title": "Matching / Couple Icons",
    "coverAssetId": "nv-012",
    "visible": false,
    "order": 4,
    "filter": {
      "type": "tags",
      "tags": [
        "matching"
      ]
    },
    "count": 0,
    "image": ""
  }
]
