[
  {
    "id": "col-001",
    "slug": "noface-icons",
    "title": "No Face, No Name",
    "description": "Anonymous and melancholic icons.",
    "coverAssetId": "nv-176",
    "tags": [
      "faceless",
      "melancholic",
      "moody",
      "anonymous",
      "candid",
      "pfp",
      "icons",
      "noface",
      "grunge",
      "emo",
      "alt",
      "anime"
    ],
    "featured": true,
    "featuredOrder": 1,
    "public": true,
    "accessNote": "",
    "assetIds": [
      "nv-025",
      "nv-127",
      "nv-128",
      "nv-130",
      "nv-131",
      "nv-132",
      "nv-136",
      "nv-138",
      "nv-140",
      "nv-143",
      "nv-146",
      "nv-148",
      "nv-150",
      "nv-151",
      "nv-152",
      "nv-155",
      "nv-159",
      "nv-160",
      "nv-161",
      "nv-170",
      "nv-173",
      "nv-174",
      "nv-176",
      "nv-180",
      "nv-181"
    ],
    "count": 25
  },
  {
    "id": "col-002",
    "slug": "anime-girl-icons",
    "title": "Anime Heroines",
    "description": "Expressive anime girl icons",
    "coverAssetId": "nv-153",
    "tags": [
      "anime",
      "anime girls",
      "girls",
      "avatars",
      "pfp",
      "icons",
      "manga",
      "illustrated",
      "cute",
      "aesthetic"
    ],
    "featured": true,
    "featuredOrder": 2,
    "public": true,
    "accessNote": "",
    "assetIds": [
      "nv-033",
      "nv-036",
      "nv-050",
      "nv-058",
      "nv-153"
    ],
    "count": 5
  },
  {
    "id": "col-003",
    "slug": "imvu-pack-01",
    "title": "IMVU pack 1",
    "description": "Aesthetic IMVU avatars",
    "coverAssetId": "nv-172",
    "tags": [
      "imvu",
      "virtual",
      "avatars",
      "gothic",
      "goth",
      "dark aesthetic",
      "alternative",
      "grunge",
      "y2k",
      "emo",
      "pfp",
      "icons"
    ],
    "featured": true,
    "featuredOrder": 3,
    "public": true,
    "accessNote": "",
    "assetIds": [
      "nv-172"
    ],
    "count": 1
  },
  {
    "id": "col-004",
    "slug": "white-minimal-banners",
    "title": "White Banners Collection",
    "description": "Bright and minimal banners",
    "coverAssetId": "nv-054",
    "tags": [
      "light",
      "bright",
      "banners",
      "minimal",
      "soft",
      "clean",
      "white",
      "pastel",
      "aesthetic",
      "header"
    ],
    "featured": true,
    "featuredOrder": 4,
    "public": true,
    "accessNote": "",
    "assetIds": [
      "nv-026",
      "nv-031",
      "nv-034",
      "nv-054",
      "nv-072",
      "nv-074",
      "nv-090",
      "nv-101",
      "nv-113",
      "nv-124",
      "nv-125"
    ],
    "count": 11
  }
]
